magnet/__init__.py
magnet/example.py
dm_magnet-0.0.1.dist-info/LICENSE
dm_magnet-0.0.1.dist-info/METADATA
dm_magnet-0.0.1.dist-info/WHEEL
dm_magnet-0.0.1.dist-info/top_level.txt
dm_magnet-0.0.1.dist-info/RECORD
