Metadata-Version: 2.1
Name: dm-magnet
Version: 0.0.1
Summary: Magnet library
Home-page: https://github.com/pypa/sampleproject
Author: Hamza Merzic, Jovana Mitrovic
Author-email: hamzamerzic@google.com, mitrovic@google.com
License: UNKNOWN
Project-URL: Bug Tracker, https://github.com/pypa/sampleproject/issues
Platform: UNKNOWN
Classifier: Programming Language :: Python :: 3
Classifier: License :: OSI Approved :: MIT License
Classifier: Operating System :: OS Independent
Requires-Python: >=3.6
License-File: LICENSE
